COPYING
MANIFEST.in
Makefile
README.md
requirements.txt
setup.cfg
setup.py
milieu/__init__.py
milieu/__main__.py
milieu/version.py
milieu.egg-info/PKG-INFO
milieu.egg-info/SOURCES.txt
milieu.egg-info/dependency_links.txt
milieu.egg-info/requires.txt
milieu.egg-info/top_level.txt