Metadata-Version: 1.0
Name: milieu
Version: 0.1.9
Summary: A helping hand to manage your settings among different environments
Home-page: https://github.com/clarete/milieu
Author: Lincoln de Sousa
Author-email: lincoln@clarete.li
License: UNKNOWN
Platform: UNKNOWN
